lovesay/__init__.py
lovesay/cli.py
lovesay/love.py
lovesay-0.3.11.dist-info/LICENSE
lovesay-0.3.11.dist-info/METADATA
lovesay-0.3.11.dist-info/WHEEL
lovesay-0.3.11.dist-info/entry_points.txt
lovesay-0.3.11.dist-info/RECORD
