Metadata-Version: 2.1
Name: lovesay
Version: 0.3.11
Summary: Cowsay, but full of love
License: MIT
Author: dotzenith
Requires-Python: >=3.9,<4.0
Classifier: License :: OSI Approved :: MIT License
Classifier: Programming Language :: Python :: 3
Classifier: Programming Language :: Python :: 3.9
Classifier: Programming Language :: Python :: 3.10
Classifier: Programming Language :: Python :: 3.11
Requires-Dist: kolorz (>=0.2.4,<0.3.0)
Requires-Dist: typer (>=0.7.0,<0.8.0)
